core/__init__.py
core/loss.py
core/metric.py
core/model.py
core/risk.py
core/training.py
pacbb-0.1.2.dist-info/LICENSE
pacbb-0.1.2.dist-info/METADATA
pacbb-0.1.2.dist-info/WHEEL
pacbb-0.1.2.dist-info/top_level.txt
pacbb-0.1.2.dist-info/RECORD
